accelerator/__init__.py
accelerator/multiget.py
accelerator/utils.py
file_dl-0.0.1.1.dist-info/DESCRIPTION.rst
file_dl-0.0.1.1.dist-info/METADATA
file_dl-0.0.1.1.dist-info/RECORD
file_dl-0.0.1.1.dist-info/WHEEL
file_dl-0.0.1.1.dist-info/entry_points.txt
file_dl-0.0.1.1.dist-info/metadata.json
file_dl-0.0.1.1.dist-info/top_level.txt
