Metadata-Version: 2.0
Name: file-dl
Version: 0.0.1.1
Summary: File Download Accelerator written in pure python
Home-page: https://github.com/animeshkundu/file-dl
Author: Animesh Kundu
Author-email: anik.edu@gmail.com
License: LICENSE.txt
Platform: UNKNOWN
Requires-Dist: futures (==3.0.5)
